pyilt2/__init__.py
pyilt2/proplist.py
pyilt2/report.py
pyilt2/version.py
pyilt22-0.9.9.data/data/man/man1/pyilt2report.1
pyilt22-0.9.9.dist-info/LICENSE
pyilt22-0.9.9.dist-info/METADATA
pyilt22-0.9.9.dist-info/WHEEL
pyilt22-0.9.9.dist-info/entry_points.txt
pyilt22-0.9.9.dist-info/top_level.txt
pyilt22-0.9.9.dist-info/RECORD
