Metadata-Version: 2.1
Name: pyilt22
Version: 0.9.9
Summary: A library to access the ILThermo v2.0 database.
Home-page: http://wgserve.de/pyilt2
Author: Frank Roemer
Author-email: froemer76@googlemail.com
License: MIT
Keywords: ILThermo,Ionic Liquids Database
Platform: UNKNOWN
Classifier: Operating System :: OS Independent
Classifier: Development Status :: 4 - Beta
Classifier: License :: OSI Approved :: MIT License
Classifier: Intended Audience :: Science/Research
Classifier: Intended Audience :: Education
Classifier: Intended Audience :: Developers
Classifier: Topic :: Database :: Front-Ends
Classifier: Topic :: Scientific/Engineering :: Chemistry
Classifier: Programming Language :: Python :: 3
Requires-Python: >=3.5
Requires-Dist: numpy (>=1.8.2)
Requires-Dist: requests (>=2.18.4)
